setup.py
importers/__init__.py
importers/abc.py
importers/lazy.py
importers/sqlite3.py
importers/zip.py
importers.egg-info/PKG-INFO
importers.egg-info/SOURCES.txt
importers.egg-info/dependency_links.txt
importers.egg-info/top_level.txt