Metadata-Version: 1.0
Name: importers
Version: 0.1.1
Summary: Various importers and utility code for writing importers
Home-page: http://importers.googlecode.com
Author: Brett Cannon
Author-email: brett@python.org
License: UNKNOWN
Platform: UNKNOWN
Classifier: Development Status :: 4 - Beta
Classifier: Programming Language :: Python
Classifier: Programming Language :: Python :: 3
Classifier: Programming Language :: Python :: 3.1
